{
  "formatVersion": 1,
  "database": {
    "version": 2,
    "identityHash": "938bd3796eb269460f4455b9aa5edf33",
    "entities": [
      {
        "tableName": "monthly_expense",
        "createSql": "CREATE TABLE IF NOT EXISTS `${TABLE_NAME}` (`yearMonth` INTEGER NOT NULL, `initialValue` TEXT NOT NULL, `savingsGoal` TEXT NOT NULL, PRIMARY KEY(`yearMonth`))",
        "fields": [
          {
            "fieldPath": "yearMonth",
            "columnName": "yearMonth",
            "affinity": "INTEGER",
            "notNull": true
          },
          {
            "fieldPath": "initialValue",
            "columnName": "initialValue",
            "affinity": "TEXT",
            "notNull": true
          },
          {
            "fieldPath": "savingsGoal",
            "columnName": "savingsGoal",
            "affinity": "TEXT",
            "notNull": true
          }
        ],
        "primaryKey": {
          "autoGenerate": false,
          "columnNames": [
            "yearMonth"
          ]
        },
        "indices": [],
        "foreignKeys": []
      },
      {
        "tableName": "entry",
        "createSql": "CREATE TABLE IF NOT EXISTS `${TABLE_NAME}` (`id` INTEGER PRIMARY KEY AUTOINCREMENT, `datetime` INTEGER NOT NULL, `amount` TEXT NOT NULL, `description` TEXT NOT NULL)",
        "fields": [
          {
            "fieldPath": "id",
            "columnName": "id",
            "affinity": "INTEGER",
            "notNull": false
          },
          {
            "fieldPath": "datetime",
            "columnName": "datetime",
            "affinity": "INTEGER",
            "notNull": true
          },
          {
            "fieldPath": "amount",
            "columnName": "amount",
            "affinity": "TEXT",
            "notNull": true
          },
          {
            "fieldPath": "description",
            "columnName": "description",
            "affinity": "TEXT",
            "notNull": true
          }
        ],
        "primaryKey": {
          "autoGenerate": true,
          "columnNames": [
            "id"
          ]
        },
        "indices": [],
        "foreignKeys": []
      }
    ],
    "views": [],
    "setupQueries": [
      "CREATE TABLE IF NOT EXISTS room_master_table (id INTEGER PRIMARY KEY,identity_hash TEXT)",
      "INSERT OR REPLACE INTO room_master_table (id,identity_hash) VALUES(42, '938bd3796eb269460f4455b9aa5edf33')"
    ]
  }
}